hlucb/__init__.py
hlucb/_hamming_lucb.py
hlucb/_plotting.py
hlucb-0.1.4.dist-info/WHEEL
hlucb-0.1.4.dist-info/METADATA
hlucb-0.1.4.dist-info/RECORD
