Metadata-Version: 2.1
Name: hlucb
Version: 0.1.4
Summary: Hamming-LUCB algorithm implementation
Home-page: https://github.com/gregorybchris/hlucb
License: Apache Software License
Keywords: hlucb,hamming,lucb,approximate,ranking,pairwise,comparisons
Author: Chris Gregory
Author-email: christopher.b.gregory@gmail.com
Requires-Python: >=3.8.1
Classifier: Development Status :: 4 - Beta
Classifier: License :: Other/Proprietary License
Classifier: Operating System :: OS Independent
Classifier: Programming Language :: Python :: 3
Classifier: Programming Language :: Python :: 3.9
Classifier: Programming Language :: Python :: 3.10
Classifier: Programming Language :: Python :: 3.11
Classifier: Programming Language :: Python :: 3.8
Classifier: Programming Language :: Python :: 3.9
Requires-Dist: numpy (>=1.24.2,<2.0.0)
Project-URL: Repository, https://github.com/gregorybchris/hlucb
